Xhpc/__init__.py
Xhpc/assess.py
Xhpc/cmd.py
Xhpc/directives.py
Xhpc/email.py
Xhpc/env.py
Xhpc/io_utils.py
Xhpc/nodes.py
Xhpc/preamble.py
Xhpc/relocate.py
Xhpc/scratches.py
Xhpc/xhpc.py
Xhpc/scripts/__init__.py
Xhpc/scripts/_standalone_xhpc.py
Xhpc/test/__init__.py
Xhpc/test/test_cmd.py
Xhpc/test/test_directives.py
Xhpc/test/test_email.py
Xhpc/test/test_env.py
Xhpc/test/test_io_utils.py
Xhpc/test/test_nodes.py
Xhpc/test/test_preamble.py
Xhpc/test/test_relocate.py
Xhpc/test/test_scratches.py
Xhpc-2.9.dist-info/LICENCE
Xhpc-2.9.dist-info/METADATA
Xhpc-2.9.dist-info/WHEEL
Xhpc-2.9.dist-info/entry_points.txt
Xhpc-2.9.dist-info/top_level.txt
Xhpc-2.9.dist-info/RECORD
