Metadata-Version: 2.1
Name: Xhpc
Version: 2.9
Summary: Xhpc is a command line tool allowing the conversion of a sh/bash script into a Slurm (or Torque) script with directives for use on a computercluster.
Home-page: https://github.com/FranckLejzerowicz/Xhpc
Author: Franck Lejzerowicz
Author-email: franck.lejzerowicz@gmail.com
Maintainer: Franck Lejzerowicz
Maintainer-email: franck.lejzerowicz@gmail.com
License: BSD
Classifier: License :: OSI Approved :: BSD License
Classifier: Topic :: Scientific/Engineering
Classifier: Topic :: Scientific/Engineering :: Bio-Informatics
Classifier: Programming Language :: Python :: 3.5
Classifier: Programming Language :: Python :: 3 :: Only
Classifier: Operating System :: Unix
Classifier: Operating System :: POSIX
Classifier: Operating System :: MacOS :: MacOS X
Requires-Python: >=3.6
License-File: LICENCE
Requires-Dist: click
Requires-Dist: pandas
Requires-Dist: PyYAML
